{
  "digest_date": "December 01, 2025",
  "articles": [
    {
      "rank": 1,
      "emoji": "📰",
      "title": "Elon Musk says robots will make work optional in new viral Optimus clip",
      "summary": "Robots Elon Musk teases a future run by robots Tesla’s Optimus montage shows robots cooking, policing and stepping into our everyday lives By Kurt Knutsson, CyberGuy Report Fox News Published November 30, 2025 7:30am EST Facebook Twitter Flipboard Comments Print Email Add Fox News on Google close Video Fox News Flash top headlines for November 29 Fox News Flash top headlines are here. Check out whats clicking on FoxNews.com. NEW You can now liste",
      "details": [
        "Source: ",
        "Category: World News",
        "Method: Fallback"
      ],
      "category": "World News",
      "source": "",
      "url": "https://www.foxnews.com/tech/elon-musk-teases-future-run-robots",
      "timeline": [
        {
          "date": "Background",
          "event": "Story develops from earlier events"
        },
        {
          "date": "Recently",
          "event": "Key developments begin to unfold"
        },
        {
          "date": "Yesterday",
          "event": "Situation reaches critical point"
        },
        {
          "date": "Today",
          "event": "Current story breaks and makes headlines"
        }
      ]
    },
    {
      "rank": 2,
      "emoji": "📰",
      "title": "Hong Kong fire : Death toll rises to 146 as thousands pay their respects",
      "summary": "Hong Kong fire death toll rises to 146 as thousands pay respects 19 hours ago Share Save Hafsa Khalil Share Save Reuters At least 146 people are now known to have died in the devastating fire that tore through high-rise buildings in Hong Kong on Wednesday. Police announced the new death toll on Sunday, cautioning that they 'cannot rule out the possibility of further fatalities'. There are still 150 people missing, and the blaze left 79 injured. S",
      "details": [
        "Source: ",
        "Category: World News",
        "Method: Fallback"
      ],
      "category": "World News",
      "source": "",
      "url": "https://www.bbc.com/news/articles/cp34yk7z6yxo",
      "timeline": [
        {
          "date": "Background",
          "event": "Story develops from earlier events"
        },
        {
          "date": "Recently",
          "event": "Key developments begin to unfold"
        },
        {
          "date": "Yesterday",
          "event": "Situation reaches critical point"
        },
        {
          "date": "Today",
          "event": "Current story breaks and makes headlines"
        }
      ]
    },
    {
      "rank": 3,
      "emoji": "📰",
      "title": "At least one killed and dozens injured in Russian strikes on Ukraine",
      "summary": "News World Ukraine At least one killed and dozens injured in Russian strikes on Ukraine Fire rages after a Russian missile hit a multi-story residential building in Vyshgorod, outside of Kyiv, Ukraine, early Sunday, Nov. 30, 2025. - Copyright Efrem Lukatsky/Copyright 2025 The AP. All rights reserved. Copyright Efrem Lukatsky/Copyright 2025 The AP. All rights reserved. By Euronews &nbspwith AP Published on 30/11/2025 - 12:24 GMT+1 Share Comments S",
      "details": [
        "Source: ",
        "Category: World News",
        "Method: Fallback"
      ],
      "category": "World News",
      "source": "",
      "url": "https://www.euronews.com/2025/11/30/at-least-one-killed-and-dozens-injured-in-russian-strikes-on-ukraine",
      "timeline": [
        {
          "date": "Background",
          "event": "Story develops from earlier events"
        },
        {
          "date": "Recently",
          "event": "Key developments begin to unfold"
        },
        {
          "date": "Yesterday",
          "event": "Situation reaches critical point"
        },
        {
          "date": "Today",
          "event": "Current story breaks and makes headlines"
        }
      ]
    },
    {
      "rank": 4,
      "emoji": "📰",
      "title": "Bangkok Post - Tropical storm deaths cross 600 in Southeast Asia , over 4m affec",
      "summary": "World Tropical storm deaths cross 600 in Southeast Asia, over 4m affected In Indonesia, helicopters deliver aid where roads are blocked PUBLISHED : 30 Nov 2025 at 17:05 UPDATED : 30 Nov 2025 at 18:58 WRITER: Reuters Small Medium Large Listen to this article Play Pause Teenagers paddle a boat on flooded paddy fields after heavy rain in Malaysia’s northern states bordering Thailand, in Kangar, Malaysia, Nov 27, 2025. (Reuters photo) JAKARTA/BANGKOK",
      "details": [
        "Source: ",
        "Category: World News",
        "Method: Fallback"
      ],
      "category": "World News",
      "source": "",
      "url": "https://www.bangkokpost.com/world/3147302/tropical-storm-deaths-cross-600-in-southeast-asia-over-4m-affected",
      "timeline": [
        {
          "date": "Background",
          "event": "Story develops from earlier events"
        },
        {
          "date": "Recently",
          "event": "Key developments begin to unfold"
        },
        {
          "date": "Yesterday",
          "event": "Situation reaches critical point"
        },
        {
          "date": "Today",
          "event": "Current story breaks and makes headlines"
        }
      ]
    },
    {
      "rank": 5,
      "emoji": "📰",
      "title": "Bangkok Post - Tropical storm deaths cross 600 in Southeast Asia , over 4m affec",
      "summary": "World Tropical storm deaths cross 600 in Southeast Asia, over 4m affected In Indonesia, helicopters deliver aid where roads are blocked PUBLISHED : 30 Nov 2025 at 17:05 UPDATED : 30 Nov 2025 at 18:58 WRITER: Reuters Small Medium Large Listen to this article Play Pause Teenagers paddle a boat on flooded paddy fields after heavy rain in Malaysia’s northern states bordering Thailand, in Kangar, Malaysia, Nov 27, 2025. (Reuters photo) JAKARTA/BANGKOK",
      "details": [
        "Source: ",
        "Category: World News",
        "Method: Fallback"
      ],
      "category": "World News",
      "source": "",
      "url": "https://www.bangkokpost.com/world/3147302/tropical-storm-deaths-cross-500-in-southeast-asia-over-4m-affected",
      "timeline": [
        {
          "date": "Background",
          "event": "Story develops from earlier events"
        },
        {
          "date": "Recently",
          "event": "Key developments begin to unfold"
        },
        {
          "date": "Yesterday",
          "event": "Situation reaches critical point"
        },
        {
          "date": "Today",
          "event": "Current story breaks and makes headlines"
        }
      ]
    },
    {
      "rank": 6,
      "emoji": "📰",
      "title": "Bangkok Post - Hong Kong in mourning as fire death toll climbs to 146",
      "summary": "World Hong Kong in mourning as fire death toll climbs to 146 PUBLISHED : 30 Nov 2025 at 20:45 WRITER: AFP Small Medium Large Listen to this article Play Pause People near Wang Fuk Court in Hong Kong mourning the world's deadliest residential building fire since 1980 HONG KONG - Crowds of mourners gathered on Sunday across Hong Kong including thousands near the apartment blocks that were engulfed in flames earlier this week, killing at least 146 p",
      "details": [
        "Source: ",
        "Category: World News",
        "Method: Fallback"
      ],
      "category": "World News",
      "source": "",
      "url": "https://www.bangkokpost.com/world/3147347/hong-kong-in-mourning-as-fire-death-toll-climbs-to-146",
      "timeline": [
        {
          "date": "Background",
          "event": "Story develops from earlier events"
        },
        {
          "date": "Recently",
          "event": "Key developments begin to unfold"
        },
        {
          "date": "Yesterday",
          "event": "Situation reaches critical point"
        },
        {
          "date": "Today",
          "event": "Current story breaks and makes headlines"
        }
      ]
    },
    {
      "rank": 7,
      "emoji": "📰",
      "title": "Bangkok Post - Indonesia says 303 dead in 3 provinces due to severe rains",
      "summary": "World Indonesia says 303 dead in 3 provinces due to severe rains PUBLISHED : 30 Nov 2025 at 12:38 WRITER: Bloomberg Small Medium Large Listen to this article Play Pause A local resident stands near debris as he inspects an area hit by deadly flash floods following heavy rains in Pidie Jaya, Aceh, Indonesia on Saturday. (Reuters photo) Indonesia’s national disaster agency has raised its death toll from the severe rains sweeping parts of the archip",
      "details": [
        "Source: ",
        "Category: World News",
        "Method: Fallback"
      ],
      "category": "World News",
      "source": "",
      "url": "https://www.bangkokpost.com/world/3147249/indonesiasays-303-dead-in-3-provinces-due-to-severe-rains",
      "timeline": [
        {
          "date": "Background",
          "event": "Story develops from earlier events"
        },
        {
          "date": "Recently",
          "event": "Key developments begin to unfold"
        },
        {
          "date": "Yesterday",
          "event": "Situation reaches critical point"
        },
        {
          "date": "Today",
          "event": "Current story breaks and makes headlines"
        }
      ]
    },
    {
      "rank": 8,
      "emoji": "📰",
      "title": "Broken heart and curdling fury as Hong Kong mourns fire victims",
      "summary": "World Asia Hong Kong ‘Broken hearts’ and curdling fury as Hong Kong mourns fire victims By Lisa Visentin and Daniel Ceng Updated November 30, 2025 — 10.52pm first published at 6.07pm Save Log in , register or subscribe to save articles for later. Save articles for later Add articles to your saved list and come back to them any time. Got it Normal text size Larger text size Very large text size Advertisement Tai Po, Hong Kong: Grief-stricken and a",
      "details": [
        "Source: ",
        "Category: World News",
        "Method: Fallback"
      ],
      "category": "World News",
      "source": "",
      "url": "https://www.smh.com.au/world/asia/broken-hearts-and-curdling-fury-as-hong-kong-mourns-fire-victims-20251130-p5njks.html",
      "timeline": [
        {
          "date": "Background",
          "event": "Story develops from earlier events"
        },
        {
          "date": "Recently",
          "event": "Key developments begin to unfold"
        },
        {
          "date": "Yesterday",
          "event": "Situation reaches critical point"
        },
        {
          "date": "Today",
          "event": "Current story breaks and makes headlines"
        }
      ]
    },
    {
      "rank": 9,
      "emoji": "📰",
      "title": "Death toll in Hong Kong apartment complex fire hits 146",
      "summary": "News Death toll in Hong Kong apartment complex fire hits 146 Another 100 people remain unaccounted for after seven high-rise buildings caught fire and continued burning for two days. Emergency crew remove what appears to be a body bag from the site of a deadly Wednesday fire at Wang Fuk Court, a residential estate in the Tai Po district of Hong Kong's New Territories on Sunday, November 30, 2025 [Ng Han Guan/AP] By News Agencies Published On 30 N",
      "details": [
        "Source: ",
        "Category: World News",
        "Method: Fallback"
      ],
      "category": "World News",
      "source": "",
      "url": "https://www.aljazeera.com/news/2025/11/30/death-toll-in-hong-kong-apartment-complex-fire-hits-146",
      "timeline": [
        {
          "date": "Background",
          "event": "Story develops from earlier events"
        },
        {
          "date": "Recently",
          "event": "Key developments begin to unfold"
        },
        {
          "date": "Yesterday",
          "event": "Situation reaches critical point"
        },
        {
          "date": "Today",
          "event": "Current story breaks and makes headlines"
        }
      ]
    },
    {
      "rank": 10,
      "emoji": "📰",
      "title": "En Californie , au moins quatre morts et dix blessés dans des tirs à larme à feu",
      "summary": "Des policiers sur les lieux de l’attaque à Stockton, en Californie, le 29 novembre 2025. FRED GREAVES / REUTERS Au moins quatre personnes sont mortes, dont trois enfants, et onze autres ont été blessées par des tirs survenus samedi 29 novembre au soir à Stockton, ville de Californie, dans l’ouest des Etats-Unis, en plein week-end prolongé de Thanksgiving, a annoncé la police en évoquant une tuerie « ciblée » . Les quatre victimes étaient âgées de",
      "details": [
        "Source: ",
        "Category: World News",
        "Method: Fallback"
      ],
      "category": "World News",
      "source": "",
      "url": "https://www.lemonde.fr/international/article/2025/11/30/en-californie-au-moins-quatre-morts-et-dix-blesses-dans-des-tirs-a-l-arme-a-feu_6655444_3210.html",
      "timeline": [
        {
          "date": "Background",
          "event": "Story develops from earlier events"
        },
        {
          "date": "Recently",
          "event": "Key developments begin to unfold"
        },
        {
          "date": "Yesterday",
          "event": "Situation reaches critical point"
        },
        {
          "date": "Today",
          "event": "Current story breaks and makes headlines"
        }
      ]
    }
  ],
  "dailyGreeting": "Good morning, today brings important global updates",
  "readingTime": "3 minute read",
  "displayDate": "MONDAY, DECEMBER 1, 2025",
  "historicalEvents": [
    {
      "year": "1485",
      "description": "Battle of Bosworth Field ends War of Roses"
    },
    {
      "year": "1864",
      "description": "Geneva Convention for wounded soldiers signed"
    },
    {
      "year": "1911",
      "description": "Mona Lisa stolen from Louvre Museum"
    },
    {
      "year": "1969",
      "description": "Apollo 11 lands on moon successfully"
    }
  ],
  "generatedAt": "2025-12-01T07:30:57.656290",
  "generatedAtUK": "2025-12-01T07:30:57.656304+00:00"
}