{
  "digest_date": "January 15, 2026",
  "articles": [
    {
      "rank": 1,
      "emoji": "📰",
      "title": "4 NASA Crew - 11 astronauts to depart ISS , leaving behind just 3 crewmates to s",
      "summary": "Video Ad Feedback 4 astronauts depart Space Station in NASA's first medical evacuation 1:21 • Source: CNN 4 astronauts depart Space Station in NASA's first medical evacuation 1:21 Trending Now 9 videos Video Ad Feedback 4 astronauts depart Space Station in NASA's first medical evacuation 1:21 • Source: CNN 4 astronauts depart Space Station in NASA's first medical evacuation 1:21 Video Ad Feedback This Georgia church says it has 72 million viewers",
      "details": [
        "Source: ",
        "Category: World News",
        "Method: Fallback"
      ],
      "category": "World News",
      "source": "",
      "url": "https://www.cnn.com/2026/01/14/science/nasa-astronauts-depart-iss-health-concern",
      "timeline": [
        {
          "date": "Background",
          "event": "Story develops from earlier events"
        },
        {
          "date": "Recently",
          "event": "Key developments begin to unfold"
        },
        {
          "date": "Yesterday",
          "event": "Situation reaches critical point"
        },
        {
          "date": "Today",
          "event": "Current story breaks and makes headlines"
        }
      ]
    },
    {
      "rank": 2,
      "emoji": "📰",
      "title": "4 NASA Crew - 11 astronauts to depart ISS , leaving behind just 3 crewmates to s",
      "summary": "Video Ad Feedback 4 astronauts depart Space Station in NASA's first medical evacuation 1:21 • Source: CNN 4 astronauts depart Space Station in NASA's first medical evacuation 1:21 Trending Now 9 videos Video Ad Feedback 4 astronauts depart Space Station in NASA's first medical evacuation 1:21 • Source: CNN 4 astronauts depart Space Station in NASA's first medical evacuation 1:21 Video Ad Feedback This Georgia church says it has 72 million viewers",
      "details": [
        "Source: ",
        "Category: World News",
        "Method: Fallback"
      ],
      "category": "World News",
      "source": "",
      "url": "https://edition.cnn.com/2026/01/14/science/nasa-astronauts-depart-iss-health-concern",
      "timeline": [
        {
          "date": "Background",
          "event": "Story develops from earlier events"
        },
        {
          "date": "Recently",
          "event": "Key developments begin to unfold"
        },
        {
          "date": "Yesterday",
          "event": "Situation reaches critical point"
        },
        {
          "date": "Today",
          "event": "Current story breaks and makes headlines"
        }
      ]
    },
    {
      "rank": 3,
      "emoji": "📰",
      "title": "Offshore wind farm contracts to power 12m united kingdom homes after record auct",
      "summary": "News UK Home News Offshore wind farm contracts to power 12m UK homes after record auction The results mark the largest procurement in European history Albert Toth Wednesday 14 January 2026 11:04 GMT Bookmark Comments Go to comments Bookmark popover Removed from bookmarks Close popover Video shows smart tips to reduce energy expenses Your support helps us to tell the story Read more Support Now From reproductive rights to climate change to Big Tec",
      "details": [
        "Source: ",
        "Category: World News",
        "Method: Fallback"
      ],
      "category": "World News",
      "source": "",
      "url": "https://www.independent.co.uk/news/uk/home-news/offshore-wind-farm-contracts-labour-where-energy-b2900223.html",
      "timeline": [
        {
          "date": "Background",
          "event": "Story develops from earlier events"
        },
        {
          "date": "Recently",
          "event": "Key developments begin to unfold"
        },
        {
          "date": "Yesterday",
          "event": "Situation reaches critical point"
        },
        {
          "date": "Today",
          "event": "Current story breaks and makes headlines"
        }
      ]
    },
    {
      "rank": 4,
      "emoji": "📰",
      "title": "Editorial | Hong Kong victims of online scams need psychological safety nets",
      "summary": "Advertisement Hong Kong society Opinion SCMP Editorial Editorial | Hong Kong’s victims of online scams need psychological safety nets As the city tackles the scourge of scams, it must pay attention to the mental health of those affected and ensure they are supported Reading Time: 2 minutes Why you can trust SCMP SCMP Editorial Published: 6:45am, 15 Jan 2026 The damage caused by scammers has long been measured in financial terms. Around HK$14 mill",
      "details": [
        "Source: ",
        "Category: World News",
        "Method: Fallback"
      ],
      "category": "World News",
      "source": "",
      "url": "https://www.scmp.com/opinion/comment/article/3339827/hong-kongs-victims-online-scams-need-psychological-safety-nets",
      "timeline": [
        {
          "date": "Background",
          "event": "Story develops from earlier events"
        },
        {
          "date": "Recently",
          "event": "Key developments begin to unfold"
        },
        {
          "date": "Yesterday",
          "event": "Situation reaches critical point"
        },
        {
          "date": "Today",
          "event": "Current story breaks and makes headlines"
        }
      ]
    },
    {
      "rank": 5,
      "emoji": "📰",
      "title": "Minnesota charter school Sejong Academy moves online citing safety concerns",
      "summary": "Minneapolis-St. Paul Taxpayer-funded Minnesota charter school shuts down in-person learning amid ICE raids Sejong Academy in St. Paul moves classes online as community group warns Myanmar immigrants to stay home By Greg Wehner Fox News Published January 14, 2026 9:43pm EST Facebook Twitter Threads Flipboard Comments Print Email Add Fox News on Google close Video More than 2,000 federal agents deployed to Minneapolis after ICE-involved shooting WA",
      "details": [
        "Source: ",
        "Category: World News",
        "Method: Fallback"
      ],
      "category": "World News",
      "source": "",
      "url": "https://www.foxnews.com/us/taxpayer-funded-minnesota-charter-school-shuts-down-person-learning-ice-raids",
      "timeline": [
        {
          "date": "Background",
          "event": "Story develops from earlier events"
        },
        {
          "date": "Recently",
          "event": "Key developments begin to unfold"
        },
        {
          "date": "Yesterday",
          "event": "Situation reaches critical point"
        },
        {
          "date": "Today",
          "event": "Current story breaks and makes headlines"
        }
      ]
    },
    {
      "rank": 6,
      "emoji": "📰",
      "title": "Keller Logistics Group Makes Its RILA Debut : Helping Retailers Restore Control ",
      "summary": "Keller Logistics Group Makes Its RILA Debut: Helping Retailers Restore Control, Reduce Cost, and Scale E-Commerce Under Pressure News provided by Keller Logistics Group, Inc. Jan 14, 2026, 15:13 ET Share this article Share to X Share this article Share to X DEFIANCE, Ohio , Jan. 14, 2026 /PRNewswire/ -- Keller Logistics Group will exhibit for the first time at the Retail Industry Leaders Association (RILA) Retail Supply Chain Conference, taking p",
      "details": [
        "Source: ",
        "Category: World News",
        "Method: Fallback"
      ],
      "category": "World News",
      "source": "",
      "url": "https://www.prnewswire.com/news-releases/keller-logistics-group-makes-its-rila-debut-helping-retailers-restore-control-reduce-cost-and-scale-e-commerce-under-pressure-302661590.html",
      "timeline": [
        {
          "date": "Background",
          "event": "Story develops from earlier events"
        },
        {
          "date": "Recently",
          "event": "Key developments begin to unfold"
        },
        {
          "date": "Yesterday",
          "event": "Situation reaches critical point"
        },
        {
          "date": "Today",
          "event": "Current story breaks and makes headlines"
        }
      ]
    },
    {
      "rank": 7,
      "emoji": "📰",
      "title": "Befragung im Bundestag : Streit um Infrastruktur - Schutz - Viele Fragen an Dobr",
      "summary": "Befragung im Bundestag : Streit um Infrastruktur-Schutz - Viele Fragen an Dobrindt 14. Januar 2026, 16:48 Uhr Quelle: dpa Berlin/Brandenburg Hinweis DIE ZEIT hat diese Meldung redaktionell nicht bearbeitet. Sie wurde automatisch von der Deutschen Presse-Agentur (dpa) übernommen. Bundesinnenminister Alexander Dobrindt (CSU) muss in der Befragung der Bundesre © Bernd von Jutrczenka/​dpa Nach dem Brandanschlag auf die Berliner Stromversorgung sieht",
      "details": [
        "Source: ",
        "Category: World News",
        "Method: Fallback"
      ],
      "category": "World News",
      "source": "",
      "url": "https://www.zeit.de/news/2026-01/14/streit-um-infrastruktur-schutz-viele-fragen-an-dobrindt",
      "timeline": [
        {
          "date": "Background",
          "event": "Story develops from earlier events"
        },
        {
          "date": "Recently",
          "event": "Key developments begin to unfold"
        },
        {
          "date": "Yesterday",
          "event": "Situation reaches critical point"
        },
        {
          "date": "Today",
          "event": "Current story breaks and makes headlines"
        }
      ]
    },
    {
      "rank": 8,
      "emoji": "📰",
      "title": "Japan PM Sanae Takaichi to dissolve Parliament for snap election next month",
      "summary": "Japan Japan's Prime Minister Takaichi plans to dissolve Parliament and call early election to strengthen coalition Sanae Takaichi plans to dissolve Parliament's lower house as early as Jan. 23 to capitalize on high popularity By Greg Wehner Fox News Published January 14, 2026 7:56pm EST Facebook Twitter Threads Flipboard Comments Print Email Add Fox News on Google close Video Trump meets with Japan’s prime minister to discuss security, investment",
      "details": [
        "Source: ",
        "Category: World News",
        "Method: Fallback"
      ],
      "category": "World News",
      "source": "",
      "url": "https://www.foxnews.com/world/japans-prime-minister-takaichi-plans-dissolve-parliament-call-early-election-strengthen-coalition",
      "timeline": [
        {
          "date": "Background",
          "event": "Story develops from earlier events"
        },
        {
          "date": "Recently",
          "event": "Key developments begin to unfold"
        },
        {
          "date": "Yesterday",
          "event": "Situation reaches critical point"
        },
        {
          "date": "Today",
          "event": "Current story breaks and makes headlines"
        }
      ]
    },
    {
      "rank": 9,
      "emoji": "📰",
      "title": "Stromausfall in Berlin : Dobrindt beharrt auf Ausweitung der Bekämpfung des Link",
      "summary": "Stromausfall in Berlin : Dobrindt beharrt auf Ausweitung der Bekämpfung des Linksterrorismus Die Opposition hat bei einer Regierungsbefragung zum Infrastrukturschutz Pläne des Bundesinnenministeriums kritisiert. Alexander Dobrindt verteidigte die Vorschläge. 14. Januar 2026, 18:07 Uhr Quelle: DIE ZEIT, dpa, bam Ihr Browser unterstützt die Wiedergabe von Audio Dateien nicht. Download der Datei als mp3: https://zon-speechbert-production.s3.eu-centr",
      "details": [
        "Source: ",
        "Category: World News",
        "Method: Fallback"
      ],
      "category": "World News",
      "source": "",
      "url": "https://www.zeit.de/politik/deutschland/2026-01/dobrindt-infrastruktur-schutz-berlin-stromausfall-linksterror",
      "timeline": [
        {
          "date": "Background",
          "event": "Story develops from earlier events"
        },
        {
          "date": "Recently",
          "event": "Key developments begin to unfold"
        },
        {
          "date": "Yesterday",
          "event": "Situation reaches critical point"
        },
        {
          "date": "Today",
          "event": "Current story breaks and makes headlines"
        }
      ]
    },
    {
      "rank": 10,
      "emoji": "📰",
      "title": "Iran protest death toll expected to rise as Tehran blames  terrorists",
      "summary": "News World Iran Iran protest death toll expected to rise as Tehran blames 'terrorists' FILE: Protesters participate in a demonstration supporting protesters in Iran, in front of the US Consulate, Milan, 13 January 2026 - Copyright AP Photo Copyright AP Photo By Euronews Parsi Published on 14/01/2026 - 16:33 GMT+1 Share Comments Share Facebook Twitter Flipboard Send Reddit Linkedin Messenger Telegram VK Bluesky Threads Whatsapp On the 18th day of",
      "details": [
        "Source: ",
        "Category: World News",
        "Method: Fallback"
      ],
      "category": "World News",
      "source": "",
      "url": "https://www.euronews.com/2026/01/14/iran-protest-death-toll-expected-to-rise-as-tehran-blames-terrorists",
      "timeline": [
        {
          "date": "Background",
          "event": "Story develops from earlier events"
        },
        {
          "date": "Recently",
          "event": "Key developments begin to unfold"
        },
        {
          "date": "Yesterday",
          "event": "Situation reaches critical point"
        },
        {
          "date": "Today",
          "event": "Current story breaks and makes headlines"
        }
      ]
    }
  ],
  "dailyGreeting": "Good morning, today brings important global updates",
  "readingTime": "3 minute read",
  "displayDate": "THURSDAY, JANUARY 15, 2026",
  "historicalEvents": [
    {
      "year": "1485",
      "description": "Battle of Bosworth Field ends War of Roses"
    },
    {
      "year": "1864",
      "description": "Geneva Convention for wounded soldiers signed"
    },
    {
      "year": "1911",
      "description": "Mona Lisa stolen from Louvre Museum"
    },
    {
      "year": "1969",
      "description": "Apollo 11 lands on moon successfully"
    }
  ],
  "generatedAt": "2026-01-15T07:35:37.728456",
  "generatedAtUK": "2026-01-15T07:35:37.728475+00:00"
}